spike/__init__.py
spike/configs/psfex_config/default.conv
spike/configs/psfex_config/default.psfex
spike/configs/psfex_config/detaileddefault.psfex
spike/configs/psfex_config/prepsfex.param
spike/configs/psfex_config/prepsfex.sex
spike/configs/sextractor_config/README
spike/configs/sextractor_config/block_3x3.conv
spike/configs/sextractor_config/default.conv
spike/configs/sextractor_config/default.nnw
spike/configs/sextractor_config/default.param
spike/configs/sextractor_config/default.sex
spike/configs/sextractor_config/default_psf.param
spike/configs/sextractor_config/default_psf.sex
spike/configs/sextractor_config/detaileddefault.sex
spike/configs/sextractor_config/gauss_1.5_3x3.conv
spike/configs/sextractor_config/gauss_2.0_3x3.conv
spike/configs/sextractor_config/gauss_2.0_5x5.conv
spike/configs/sextractor_config/gauss_2.5_5x5.conv
spike/configs/sextractor_config/gauss_3.0_5x5.conv
spike/configs/sextractor_config/gauss_3.0_7x7.conv
spike/configs/sextractor_config/gauss_4.0_7x7.conv
spike/configs/sextractor_config/gauss_5.0_9x9.conv
spike/configs/sextractor_config/mexhat_1.5_5x5.conv
spike/configs/sextractor_config/mexhat_2.0_7x7.conv
spike/configs/sextractor_config/mexhat_2.5_7x7.conv
spike/configs/sextractor_config/mexhat_3.0_9x9.conv
spike/configs/sextractor_config/mexhat_4.0_9x9.conv
spike/configs/sextractor_config/mexhat_5.0_11x11.conv
spike/configs/sextractor_config/tophat_1.5_3x3.conv
spike/configs/sextractor_config/tophat_2.0_3x3.conv
spike/configs/sextractor_config/tophat_2.5_3x3.conv
spike/configs/sextractor_config/tophat_3.0_3x3.conv
spike/configs/sextractor_config/tophat_4.0_5x5.conv
spike/configs/sextractor_config/tophat_5.0_5x5.conv
spike/jwstcal/__init__.py
spike/jwstcal/assign_wcs_util.py
spike/jwstcal/associations_asn_from_list.py
spike/jwstcal/associations_association.py
spike/jwstcal/associations_config.py
spike/jwstcal/associations_exceptions.py
spike/jwstcal/associations_lib_acid.py
spike/jwstcal/associations_lib_callback_registry.py
spike_psf-1.2.0.dist-info/licenses/LICENSE
spike_psf-1.2.0.dist-info/METADATA
spike_psf-1.2.0.dist-info/WHEEL
spike_psf-1.2.0.dist-info/top_level.txt
spike_psf-1.2.0.dist-info/RECORD
